liquidlib/__init__.py
liquidlib/core.py
liquidlib/adapters/__init__.py
liquidlib/adapters/analyze_pipetting_data.py
liquidlib/adapters/compare_simulations.sh
liquidlib/adapters/opentrons.py
liquidlib/adapters/prediction.py
liquidlib/liquids/__init__.py
liquidlib/liquids/dmso.py
liquidlib/liquids/ethanol.py
liquidlib/liquids/glycerin.py
liquidlib/liquids/water.py
liquidlib-0.1.3.data/data/py.typed
liquidlib-0.1.3.dist-info/METADATA
liquidlib-0.1.3.dist-info/WHEEL
liquidlib-0.1.3.dist-info/licenses/LICENSE
liquidlib-0.1.3.dist-info/RECORD
