Metadata-Version: 2.4
Name: liquidlib
Version: 0.1.3
Summary: A library for handling liquid properties and pipetting parameters
Project-URL: Homepage, https://github.com/LiquidLib/liquidlib
Project-URL: Bug Tracker, https://github.com/LiquidLib/liquidlib/issues
Author-email: Roman Gurovich <romangurovich@gmail.com>
License-File: LICENSE
Keywords: lab automation,laboratory,liquid,robotics
Classifier: Development Status :: 4 - Beta
Classifier: Intended Audience :: Science/Research
Classifier: License :: OSI Approved :: MIT License
Classifier: Operating System :: OS Independent
Classifier: Programming Language :: Python :: 3
Classifier: Programming Language :: Python :: 3.10
Classifier: Programming Language :: Python :: 3.11
Classifier: Programming Language :: Python :: 3.12
Classifier: Topic :: Scientific/Engineering
Classifier: Topic :: Scientific/Engineering :: Bio-Informatics
Classifier: Topic :: Scientific/Engineering :: Chemistry
Classifier: Topic :: Scientific/Engineering :: Hydrology
Classifier: Typing :: Typed
Requires-Python: >=3.10
Requires-Dist: opentrons>=6.0.0
Requires-Dist: pandas>=1.3.0
Provides-Extra: dev
Requires-Dist: black>=23.0; extra == 'dev'
Requires-Dist: isort>=5.0; extra == 'dev'
Requires-Dist: mypy>=1.0; extra == 'dev'
Requires-Dist: pytest-cov>=4.0; extra == 'dev'
Requires-Dist: pytest>=7.0; extra == 'dev'
Requires-Dist: ruff>=0.1.0; extra == 'dev'
